ionlab/__init__.py
ionlab/common.py
ionlab/conf.py
ionlab/IonicEquilibrium/analyze_solution.py
ionlab/IonicEquilibrium/db/chemicals.db
ionlab/IonicEquilibrium/db/chemicals.xlsx
ionlab/IonicEquilibrium/db/common_chemicals.py
ionlab/IonicEquilibrium/db/dbmanage.py
ionlab/IonicEquilibrium/db/matter.py
ionlab/IonicEquilibrium/db/process.py
ionlab/IonicEquilibrium/solver/gekko_solver.py
ionlab/IonicEquilibrium/solver/wolfram_solver.py
ionlab/IonicEquilibrium/unittest/eqtest.py
ionlab/IonicEquilibrium/utils/extension.py
ionlab-0.1.0.dist-info/LICENSE
ionlab-0.1.0.dist-info/METADATA
ionlab-0.1.0.dist-info/WHEEL
ionlab-0.1.0.dist-info/RECORD
