Metadata-Version: 2.1
Name: ionlab
Version: 0.1.0
Summary: Determine the composition of ionic equilibrium in solutions, in an ideal environment.
License: LGPL-3.0-or-later
Keywords: chemistry,ion,equilibrium,ionic,solution,analytical chemistry
Author: Nguyễn Minh Trí
Author-email: kamitri.tnyn@gmail.com
Requires-Python: >=3.11,<3.12
Classifier: Development Status :: 3 - Alpha
Classifier: Intended Audience :: Education
Classifier: Intended Audience :: Science/Research
Classifier: License :: OSI Approved :: GNU Lesser General Public License v3 or later (LGPLv3+)
Classifier: Operating System :: OS Independent
Classifier: Programming Language :: Python :: 3
Classifier: Programming Language :: Python :: 3.11
Classifier: Programming Language :: Python :: 3
Classifier: Programming Language :: Python :: 3.11
Classifier: Topic :: Scientific/Engineering :: Chemistry
Requires-Dist: gekko (==1.0.6)
Requires-Dist: matplotlib (==3.6.3)
Requires-Dist: numpy (==1.24.2)
Requires-Dist: openpyxl (==3.1.0)
Requires-Dist: pandas (==1.5.3)
Requires-Dist: sympy (==1.11.1)
Requires-Dist: wolframclient (==1.1.7)
Project-URL: Bug Tracker, https://github.com/Kamitri/ionlab/issues
Project-URL: Homepage, https://github.com/Kamitri/ionlab
